pod_common/__init__.py
pod_common/common.py
pod_common/json_schema.json
pod_common/services.ini
pod_common/services.json
pod_common/version.py
pod_common-1.0.2.dist-info/LICENSE
pod_common-1.0.2.dist-info/METADATA
pod_common-1.0.2.dist-info/WHEEL
pod_common-1.0.2.dist-info/top_level.txt
pod_common-1.0.2.dist-info/RECORD
